<?xml version="1.0" encoding="utf-8" ?>
<c2layout>
    <name>Start</name>
    <sid>857887139899298</sid>
    <event-sheet>ES_start</event-sheet>
    <size>
        <width>1920</width>
        <height>1080</height>
    </size>
    <margins>
        <horizontal>500</horizontal>
        <vertical>500</vertical>
    </margins>
    <unbounded-scrolling>0</unbounded-scrolling>
    <layers>
        <layer name="title" sid="377134819190320">
            <initially-visible>1</initially-visible>
            <background-color>0,0,119</background-color>
            <transparent>0</transparent>
            <parallax>
                <x>1</x>
                <y>1</y>
            </parallax>
            <zoom-rate>1</zoom-rate>
            <opacity>1</opacity>
            <force-own-texture>0</force-own-texture>
            <global>0</global>
            <use-render-cells>0</use-render-cells>
            <blend-mode>0</blend-mode>
            <effect-fallback>0</effect-fallback>
            <instances>
                <instance type="spr_title" uid="123">
                    <properties>
                        <text>TITLE</text>
                        <initial-visibility>Visible</initial-visibility>
                        <font>Arial,-96,400,0</font>
                        <color>0,255,0</color>
                        <horizontal-alignment>Center</horizontal-alignment>
                        <vertical-alignment>Center</vertical-alignment>
                        <hotspot>Top-left</hotspot>
                        <wrapping>Word</wrapping>
                        <line-height>0</line-height>
                    </properties>
                    <blend-mode>0</blend-mode>
                    <effect-fallback>0</effect-fallback>
                    <world>
                        <x>668.5</x>
                        <y>68</y>
                        <z>0</z>
                        <width>583</width>
                        <height>174</height>
                        <depth>0</depth>
                        <hotspotX>0</hotspotX>
                        <hotspotY>0</hotspotY>
                        <angle>0</angle>
                        <opacity>1</opacity>
                    </world>
                </instance>
                <instance type="btn_options" uid="130">
                    <properties>
                        <type>Button</type>
                        <text>Options</text>
                        <tooltip></tooltip>
                        <initial-visibility>Visible</initial-visibility>
                        <enabled>Yes</enabled>
                        <auto-font-size>Yes</auto-font-size>
                        <id-optional></id-optional>
                        <checked>No</checked>
                    </properties>
                    <blend-mode>0</blend-mode>
                    <effect-fallback>0</effect-fallback>
                    <world>
                        <x>800</x>
                        <y>588</y>
                        <z>0</z>
                        <width>320</width>
                        <height>32</height>
                        <depth>0</depth>
                        <hotspotX>0</hotspotX>
                        <hotspotY>0</hotspotY>
                    </world>
                </instance>
                <instance type="btn_skirmish" uid="131">
                    <properties>
                        <type>Button</type>
                        <text>Skirmish</text>
                        <tooltip></tooltip>
                        <initial-visibility>Visible</initial-visibility>
                        <enabled>No</enabled>
                        <auto-font-size>Yes</auto-font-size>
                        <id-optional></id-optional>
                        <checked>No</checked>
                    </properties>
                    <blend-mode>0</blend-mode>
                    <effect-fallback>0</effect-fallback>
                    <world>
                        <x>800</x>
                        <y>460</y>
                        <z>0</z>
                        <width>320</width>
                        <height>32</height>
                        <depth>0</depth>
                        <hotspotX>0</hotspotX>
                        <hotspotY>0</hotspotY>
                    </world>
                </instance>
                <instance type="btn_shipYard" uid="132">
                    <properties>
                        <type>Button</type>
                        <text>Shipyard</text>
                        <tooltip></tooltip>
                        <initial-visibility>Visible</initial-visibility>
                        <enabled>Yes</enabled>
                        <auto-font-size>Yes</auto-font-size>
                        <id-optional></id-optional>
                        <checked>No</checked>
                    </properties>
                    <blend-mode>0</blend-mode>
                    <effect-fallback>0</effect-fallback>
                    <world>
                        <x>800</x>
                        <y>524</y>
                        <z>0</z>
                        <width>320</width>
                        <height>32</height>
                        <depth>0</depth>
                        <hotspotX>0</hotspotX>
                        <hotspotY>0</hotspotY>
                    </world>
                </instance>
                <instance type="btn_camp" uid="133">
                    <properties>
                        <type>Button</type>
                        <text>Campaign</text>
                        <tooltip></tooltip>
                        <initial-visibility>Visible</initial-visibility>
                        <enabled>No</enabled>
                        <auto-font-size>Yes</auto-font-size>
                        <id-optional></id-optional>
                        <checked>No</checked>
                    </properties>
                    <blend-mode>0</blend-mode>
                    <effect-fallback>0</effect-fallback>
                    <world>
                        <x>800</x>
                        <y>396</y>
                        <z>0</z>
                        <width>320</width>
                        <height>32</height>
                        <depth>0</depth>
                        <hotspotX>0</hotspotX>
                        <hotspotY>0</hotspotY>
                    </world>
                </instance>
                <instance type="btn_exit" uid="134">
                    <properties>
                        <type>Button</type>
                        <text>Exit</text>
                        <tooltip></tooltip>
                        <initial-visibility>Visible</initial-visibility>
                        <enabled>Yes</enabled>
                        <auto-font-size>Yes</auto-font-size>
                        <id-optional></id-optional>
                        <checked>No</checked>
                    </properties>
                    <blend-mode>0</blend-mode>
                    <effect-fallback>0</effect-fallback>
                    <world>
                        <x>800</x>
                        <y>652</y>
                        <z>0</z>
                        <width>320</width>
                        <height>32</height>
                        <depth>0</depth>
                        <hotspotX>0</hotspotX>
                        <hotspotY>0</hotspotY>
                    </world>
                </instance>
                <instance type="btn_cont" uid="219">
                    <properties>
                        <type>Button</type>
                        <text>Continue</text>
                        <tooltip></tooltip>
                        <initial-visibility>Invisible</initial-visibility>
                        <enabled>Yes</enabled>
                        <auto-font-size>Yes</auto-font-size>
                        <id-optional></id-optional>
                        <checked>No</checked>
                    </properties>
                    <instance-variables>
                        <saveText></saveText>
                    </instance-variables>
                    <blend-mode>0</blend-mode>
                    <effect-fallback>0</effect-fallback>
                    <world>
                        <x>801</x>
                        <y>335</y>
                        <z>0</z>
                        <width>320</width>
                        <height>32</height>
                        <depth>0</depth>
                        <hotspotX>0</hotspotX>
                        <hotspotY>0</hotspotY>
                    </world>
                </instance>
            </instances>
            <effects />
        </layer>
    </layers>
    <nonworld-instances>
        <instance type="arr_InvPCship" uid="136">
            <properties>
                <width>1</width>
                <height>37</height>
                <depth>3</depth>
            </properties>
            <instance-variables>
                <source>pc</source>
            </instance-variables>
        </instance>
        <instance type="csv_dicPlaceDef" uid="188">
            <properties>
                <delimiter>,</delimiter>
                <eval-mode>No</eval-mode>
            </properties>
        </instance>
        <instance type="enemyInventory" uid="92">
            <properties>
                <width>0</width>
                <height>32</height>
                <depth>1</depth>
            </properties>
            <instance-variables>
                <Type>0</Type>
                <Engine>1</Engine>
                <Hull0>2</Hull0>
                <Hull1>3</Hull1>
                <Hull2>4</Hull2>
                <Hull3>5</Hull3>
                <Hull4>6</Hull4>
                <Prow0>7</Prow0>
                <Prow1>8</Prow1>
                <Prow2>9</Prow2>
                <Prow3>10</Prow3>
                <Prow4>11</Prow4>
                <SB0>12</SB0>
                <SB1>13</SB1>
                <SB2>14</SB2>
                <SB3>15</SB3>
                <SB4>16</SB4>
                <Aft0>17</Aft0>
                <Aft1>18</Aft1>
                <Aft2>19</Aft2>
                <Aft3>20</Aft3>
                <Aft4>21</Aft4>
                <Port0>22</Port0>
                <Port1>23</Port1>
                <Port2>24</Port2>
                <Port3>25</Port3>
                <Port4>26</Port4>
                <Shield1>27</Shield1>
                <Shield2>28</Shield2>
                <Shield3>29</Shield3>
                <Shield4>30</Shield4>
                <Range>31</Range>
            </instance-variables>
        </instance>
        <instance type="arr_All_Items" uid="94">
            <properties>
                <width>0</width>
                <height>3</height>
                <depth>1</depth>
            </properties>
            <instance-variables>
                <name>0</name>
                <type>1</type>
                <ID>2</ID>
            </instance-variables>
        </instance>
        <instance type="arr_enemyInventory" uid="108">
            <properties>
                <width>0</width>
                <height>38</height>
                <depth>1</depth>
            </properties>
            <instance-variables>
                <Type>0</Type>
                <Engine>1</Engine>
                <Hull0>2</Hull0>
                <Hull1>3</Hull1>
                <Hull2>4</Hull2>
                <Hull3>5</Hull3>
                <Hull4>6</Hull4>
                <Prow0>7</Prow0>
                <Prow1>8</Prow1>
                <Prow2>9</Prow2>
                <Prow3>10</Prow3>
                <Prow4>11</Prow4>
                <SB0>12</SB0>
                <SB1>13</SB1>
                <SB2>14</SB2>
                <SB3>15</SB3>
                <SB4>16</SB4>
                <Aft0>17</Aft0>
                <Aft1>18</Aft1>
                <Aft2>19</Aft2>
                <Aft3>20</Aft3>
                <Aft4>21</Aft4>
                <Port0>22</Port0>
                <Port1>23</Port1>
                <Port2>24</Port2>
                <Port3>25</Port3>
                <Port4>26</Port4>
                <Range>27</Range>
                <armor_0>28</armor_0>
                <armor_1>29</armor_1>
                <armor_2>30</armor_2>
                <armor_3>31</armor_3>
                <armor_4>32</armor_4>
                <shield_1>33</shield_1>
                <shield_2>34</shield_2>
                <shield_3>35</shield_3>
                <shield_4>36</shield_4>
                <Name>37</Name>
            </instance-variables>
        </instance>
        <instance type="arr_HitLocations" uid="107">
            <properties>
                <width>0</width>
                <height>4</height>
                <depth>1</depth>
            </properties>
            <instance-variables>
                <Front>0</Front>
                <Starboard>1</Starboard>
                <Aft>2</Aft>
                <Port>3</Port>
            </instance-variables>
        </instance>
        <instance type="arr_items_Engines" uid="62">
            <properties>
                <width>0</width>
                <height>5</height>
                <depth>1</depth>
            </properties>
            <instance-variables>
                <id>0</id>
                <engine>1</engine>
                <mass>2</mass>
                <power>3</power>
                <RechargeRate>4</RechargeRate>
            </instance-variables>
        </instance>
        <instance type="arr_items_Equip" uid="34">
            <properties>
                <width>0</width>
                <height>4</height>
                <depth>1</depth>
            </properties>
            <instance-variables>
                <id>0</id>
                <name>1</name>
                <mass>2</mass>
                <power>3</power>
            </instance-variables>
        </instance>
        <instance type="arr_items_Weapons" uid="35">
            <properties>
                <width>0</width>
                <height>7</height>
                <depth>1</depth>
            </properties>
            <instance-variables>
                <id>0</id>
                <name>1</name>
                <damage>2</damage>
                <range>3</range>
                <mass>4</mass>
                <heat>5</heat>
                <cooldown>6</cooldown>
            </instance-variables>
        </instance>
        <instance type="arr_PCShipAft" uid="47">
            <properties>
                <width>0</width>
                <height>7</height>
                <depth>2</depth>
            </properties>
            <instance-variables>
                <place>3</place>
                <shldID>999</shldID>
                <Inventory>0</Inventory>
                <ID>1</ID>
                <Damage>2</Damage>
                <Range>3</Range>
                <Power>4</Power>
                <Cooldown>5</Cooldown>
            </instance-variables>
        </instance>
        <instance type="arr_PCShipHull" uid="48">
            <properties>
                <width>0</width>
                <height>7</height>
                <depth>2</depth>
            </properties>
            <instance-variables>
                <place>0</place>
                <shldID>999</shldID>
                <Inventory>0</Inventory>
                <ID>1</ID>
                <Damage>2</Damage>
                <Range>3</Range>
                <Power>4</Power>
                <Cooldown>5</Cooldown>
            </instance-variables>
        </instance>
        <instance type="arr_PCShipEngine" uid="52">
            <properties>
                <width>0</width>
                <height>6</height>
                <depth>1</depth>
            </properties>
            <instance-variables>
                <EngineID>0</EngineID>
                <ShipType>1</ShipType>
                <acc>2</acc>
                <maxSpeed>3</maxSpeed>
                <power>4</power>
                <recharge>5</recharge>
            </instance-variables>
        </instance>
        <instance type="arr_PCShipPort" uid="49">
            <properties>
                <width>0</width>
                <height>7</height>
                <depth>2</depth>
            </properties>
            <instance-variables>
                <place>4</place>
                <shldID>999</shldID>
                <Inventory>0</Inventory>
                <ID>1</ID>
                <Damage>2</Damage>
                <Range>3</Range>
                <Power>4</Power>
                <Cooldown>5</Cooldown>
            </instance-variables>
        </instance>
        <instance type="arr_PCShipProw" uid="50">
            <properties>
                <width>0</width>
                <height>7</height>
                <depth>2</depth>
            </properties>
            <instance-variables>
                <place>1</place>
                <shldID>999</shldID>
                <Inventory>0</Inventory>
                <ID>1</ID>
                <Damage>2</Damage>
                <Range>3</Range>
                <Power>4</Power>
                <Cooldown>5</Cooldown>
            </instance-variables>
        </instance>
        <instance type="arr_PCShipSB" uid="51">
            <properties>
                <width>0</width>
                <height>7</height>
                <depth>2</depth>
            </properties>
            <instance-variables>
                <place>2</place>
                <shldID>999</shldID>
                <Inventory>0</Inventory>
                <ID>1</ID>
                <Damage>2</Damage>
                <Range>3</Range>
                <Power>4</Power>
                <Cooldown>5</Cooldown>
            </instance-variables>
        </instance>
        <instance type="arr_shipsDB" uid="41">
            <properties>
                <width>0</width>
                <height>16</height>
                <depth>1</depth>
            </properties>
            <instance-variables>
                <id>0</id>
                <type>1</type>
                <hardpoints>2</hardpoints>
                <aft>3</aft>
                <hull>4</hull>
                <port>5</port>
                <starboard>6</starboard>
                <prow>7</prow>
                <tonnage>8</tonnage>
                <DCbonus>9</DCbonus>
                <rotateSpeed>10</rotateSpeed>
                <armor_0>11</armor_0>
                <armor_1>12</armor_1>
                <armor_2>13</armor_2>
                <armor_3>14</armor_3>
                <armor_4>15</armor_4>
            </instance-variables>
        </instance>
    </nonworld-instances>
    <effects />
</c2layout>
