<?xml version="1.0" encoding="utf-8" ?>
<c2eventsheet>
    <!--All the 'name' attributes are ignored by Construct 2 - they are there for readability only.-->
    <name>Array_Functions_old</name>
    <events>
        <event-block sid="8868253682178944">
            <conditions>
                <condition id="0" name="On function" sid="8548575176652340" type="Function">
                    <param id="0" name="Name">&quot;Createitems_Equip&quot;</param>
                </condition>
            </conditions>
            <actions />
            <sub-events>
                <variable constant="0" name="localUID" sid="2834032887703001" static="0" type="number">0</variable>
                <event-block sid="7103626024168844">
                    <conditions>
                        <condition id="-8" name="Compare two values" sid="7059603426980476" type="System">
                            <param id="0" name="First value">Function.ParamCount</param>
                            <param id="1" name="Comparison">4</param>
                            <param id="2" name="Second value">0</param>
                        </condition>
                    </conditions>
                    <actions>
                        <action id="-9" name="Set value" sid="5570314013152690" type="System">
                            <param id="0" name="Variable">localUID</param>
                            <param id="1" name="Value">Function.Param(0)</param>
                        </action>
                    </actions>
                </event-block>
                <event-block sid="3232505675192897">
                    <conditions>
                        <condition id="-22" name="Else" sid="7402031664729825" type="System" />
                    </conditions>
                    <actions>
                        <action id="-3" name="Create object" sid="6957140501279473" type="System">
                            <param id="0" name="Object to create">arr_items_Equip</param>
                            <param id="1" name="Layer">0</param>
                            <param id="2" name="X">0</param>
                            <param id="3" name="Y">0</param>
                        </action>
                        <action id="-9" name="Set value" sid="3487679916602279" type="System">
                            <param id="0" name="Variable">localUID</param>
                            <param id="1" name="Value">arr_items_Equip.UID</param>
                        </action>
                    </actions>
                </event-block>
                <event-block sid="2533325245190461">
                    <conditions>
                        <condition id="-14" name="Pick by unique ID" sid="7484958995657928" type="arr_items_Equip">
                            <param id="0" name="Unique ID">localUID</param>
                        </condition>
                    </conditions>
                    <actions>
                        <action id="1" name="Set return value" sid="3344130185215097" type="Function">
                            <param id="0" name="Value">localUID</param>
                        </action>
                    </actions>
                    <sub-events>
                        <event-block sid="9538329763475054">
                            <conditions />
                            <actions>
                                <action id="1" name="Set size" sid="2357920347642649" type="arr_items_Equip">
                                    <param id="0" name="Width">arr_items_Equip.Width+1</param>
                                    <param id="1" name="Height">arr_items_Equip.Height</param>
                                    <param id="2" name="Depth">1</param>
                                </action>
                                <action id="3" name="Set at XY" sid="6952634037779257" type="arr_items_Equip">
                                    <param id="0" name="X">arr_items_Equip.Width-1</param>
                                    <param id="1" name="Y">0</param>
                                    <param id="2" name="Value">&quot;heat sink&quot;</param>
                                </action>
                                <action id="3" name="Set at XY" sid="881417749466549" type="arr_items_Equip">
                                    <param id="0" name="X">arr_items_Equip.Width-1</param>
                                    <param id="1" name="Y">1</param>
                                    <param id="2" name="Value">5</param>
                                </action>
                            </actions>
                        </event-block>
                        <event-block sid="9416427995324231">
                            <conditions />
                            <actions>
                                <action id="1" name="Set size" sid="1844824428769748" type="arr_items_Equip">
                                    <param id="0" name="Width">arr_items_Equip.Width+1</param>
                                    <param id="1" name="Height">arr_items_Equip.Height</param>
                                    <param id="2" name="Depth">1</param>
                                </action>
                                <action id="3" name="Set at XY" sid="2784183809297422" type="arr_items_Equip">
                                    <param id="0" name="X">arr_items_Equip.Width-1</param>
                                    <param id="1" name="Y">0</param>
                                    <param id="2" name="Value">&quot;ECM&quot;</param>
                                </action>
                                <action id="3" name="Set at XY" sid="5347001606454191" type="arr_items_Equip">
                                    <param id="0" name="X">arr_items_Equip.Width-1</param>
                                    <param id="1" name="Y">1</param>
                                    <param id="2" name="Value">10</param>
                                </action>
                            </actions>
                        </event-block>
                        <event-block sid="507389256380577">
                            <conditions />
                            <actions>
                                <action id="1" name="Set size" sid="6516277252453739" type="arr_items_Equip">
                                    <param id="0" name="Width">arr_items_Equip.Width+1</param>
                                    <param id="1" name="Height">arr_items_Equip.Height</param>
                                    <param id="2" name="Depth">1</param>
                                </action>
                                <action id="3" name="Set at XY" sid="92449632246354" type="arr_items_Equip">
                                    <param id="0" name="X">arr_items_Equip.Width-1</param>
                                    <param id="1" name="Y">0</param>
                                    <param id="2" name="Value">&quot;ECCM&quot;</param>
                                </action>
                                <action id="3" name="Set at XY" sid="9788038377103487" type="arr_items_Equip">
                                    <param id="0" name="X">arr_items_Equip.Width-1</param>
                                    <param id="1" name="Y">1</param>
                                    <param id="2" name="Value">15</param>
                                </action>
                            </actions>
                        </event-block>
                        <event-block sid="2480643264205352">
                            <conditions />
                            <actions>
                                <action id="1" name="Set size" sid="7066959615463829" type="arr_items_Equip">
                                    <param id="0" name="Width">arr_items_Equip.Width+1</param>
                                    <param id="1" name="Height">arr_items_Equip.Height</param>
                                    <param id="2" name="Depth">1</param>
                                </action>
                                <action id="3" name="Set at XY" sid="3422558436260774" type="arr_items_Equip">
                                    <param id="0" name="X">arr_items_Equip.Width-1</param>
                                    <param id="1" name="Y">0</param>
                                    <param id="2" name="Value">&quot;TC1&quot;</param>
                                </action>
                                <action id="3" name="Set at XY" sid="1933728741809687" type="arr_items_Equip">
                                    <param id="0" name="X">arr_items_Equip.Width-1</param>
                                    <param id="1" name="Y">1</param>
                                    <param id="2" name="Value">5</param>
                                </action>
                            </actions>
                        </event-block>
                        <event-block sid="1370036111222353">
                            <conditions />
                            <actions>
                                <action id="1" name="Set size" sid="8044491165837747" type="arr_items_Equip">
                                    <param id="0" name="Width">arr_items_Equip.Width+1</param>
                                    <param id="1" name="Height">arr_items_Equip.Height</param>
                                    <param id="2" name="Depth">1</param>
                                </action>
                                <action id="3" name="Set at XY" sid="7447073821169541" type="arr_items_Equip">
                                    <param id="0" name="X">arr_items_Equip.Width-1</param>
                                    <param id="1" name="Y">0</param>
                                    <param id="2" name="Value">&quot;TC2&quot;</param>
                                </action>
                                <action id="3" name="Set at XY" sid="5429142116355344" type="arr_items_Equip">
                                    <param id="0" name="X">arr_items_Equip.Width-1</param>
                                    <param id="1" name="Y">1</param>
                                    <param id="2" name="Value">7</param>
                                </action>
                            </actions>
                        </event-block>
                        <event-block sid="7547873076137520">
                            <conditions />
                            <actions>
                                <action id="1" name="Set size" sid="672555312643739" type="arr_items_Equip">
                                    <param id="0" name="Width">arr_items_Equip.Width+1</param>
                                    <param id="1" name="Height">arr_items_Equip.Height</param>
                                    <param id="2" name="Depth">1</param>
                                </action>
                                <action id="3" name="Set at XY" sid="6783062701152945" type="arr_items_Equip">
                                    <param id="0" name="X">arr_items_Equip.Width-1</param>
                                    <param id="1" name="Y">0</param>
                                    <param id="2" name="Value">&quot;TC3&quot;</param>
                                </action>
                                <action id="3" name="Set at XY" sid="4358518191551979" type="arr_items_Equip">
                                    <param id="0" name="X">arr_items_Equip.Width-1</param>
                                    <param id="1" name="Y">1</param>
                                    <param id="2" name="Value">12</param>
                                </action>
                            </actions>
                        </event-block>
                    </sub-events>
                </event-block>
            </sub-events>
        </event-block>
        <event-block sid="2269680340233002">
            <conditions>
                <condition id="0" name="On function" sid="8000254597391661" type="Function">
                    <param id="0" name="Name">&quot;Createitems_Weapons&quot;</param>
                </condition>
            </conditions>
            <actions />
            <sub-events>
                <variable constant="0" name="localUID" sid="4220359521459478" static="0" type="number">0</variable>
                <event-block sid="1371866781095127">
                    <conditions>
                        <condition id="-8" name="Compare two values" sid="3091808315711854" type="System">
                            <param id="0" name="First value">Function.ParamCount</param>
                            <param id="1" name="Comparison">4</param>
                            <param id="2" name="Second value">0</param>
                        </condition>
                    </conditions>
                    <actions>
                        <action id="-9" name="Set value" sid="9477952755114901" type="System">
                            <param id="0" name="Variable">localUID</param>
                            <param id="1" name="Value">Function.Param(0)</param>
                        </action>
                    </actions>
                </event-block>
                <event-block sid="8719560144939569">
                    <conditions>
                        <condition id="-22" name="Else" sid="5690357872538681" type="System" />
                    </conditions>
                    <actions>
                        <action id="-3" name="Create object" sid="4524769346255970" type="System">
                            <param id="0" name="Object to create">arr_items_Weapons</param>
                            <param id="1" name="Layer">0</param>
                            <param id="2" name="X">0</param>
                            <param id="3" name="Y">0</param>
                        </action>
                        <action id="-9" name="Set value" sid="8168098392120727" type="System">
                            <param id="0" name="Variable">localUID</param>
                            <param id="1" name="Value">arr_items_Weapons.UID</param>
                        </action>
                    </actions>
                </event-block>
                <event-block sid="5883222966672238">
                    <conditions>
                        <condition id="-14" name="Pick by unique ID" sid="4547001478454626" type="arr_items_Weapons">
                            <param id="0" name="Unique ID">localUID</param>
                        </condition>
                    </conditions>
                    <actions>
                        <action id="1" name="Set return value" sid="3497037696143116" type="Function">
                            <param id="0" name="Value">localUID</param>
                        </action>
                    </actions>
                    <sub-events>
                        <event-block sid="9385256573637750">
                            <conditions />
                            <actions>
                                <action id="1" name="Set size" sid="3937358078748616" type="arr_items_Weapons">
                                    <param id="0" name="Width">arr_items_Weapons.Width+1</param>
                                    <param id="1" name="Height">arr_items_Weapons.Height</param>
                                    <param id="2" name="Depth">1</param>
                                </action>
                                <action id="3" name="Set at XY" sid="7751773883067382" type="arr_items_Weapons">
                                    <param id="0" name="X">arr_items_Weapons.Width-1</param>
                                    <param id="1" name="Y">0</param>
                                    <param id="2" name="Value">&quot;small laser&quot;</param>
                                </action>
                                <action id="3" name="Set at XY" sid="1114733358747270" type="arr_items_Weapons">
                                    <param id="0" name="X">arr_items_Weapons.Width-1</param>
                                    <param id="1" name="Y">1</param>
                                    <param id="2" name="Value">5</param>
                                </action>
                                <action id="3" name="Set at XY" sid="2069132554995133" type="arr_items_Weapons">
                                    <param id="0" name="X">arr_items_Weapons.Width-1</param>
                                    <param id="1" name="Y">2</param>
                                    <param id="2" name="Value">10</param>
                                </action>
                                <action id="3" name="Set at XY" sid="9537568342699915" type="arr_items_Weapons">
                                    <param id="0" name="X">arr_items_Weapons.Width-1</param>
                                    <param id="1" name="Y">3</param>
                                    <param id="2" name="Value">1</param>
                                </action>
                                <action id="3" name="Set at XY" sid="6936780785934473" type="arr_items_Weapons">
                                    <param id="0" name="X">arr_items_Weapons.Width-1</param>
                                    <param id="1" name="Y">4</param>
                                    <param id="2" name="Value">1</param>
                                </action>
                            </actions>
                        </event-block>
                        <event-block sid="5451804622597366">
                            <conditions />
                            <actions>
                                <action id="1" name="Set size" sid="2335765056807599" type="arr_items_Weapons">
                                    <param id="0" name="Width">arr_items_Weapons.Width+1</param>
                                    <param id="1" name="Height">arr_items_Weapons.Height</param>
                                    <param id="2" name="Depth">1</param>
                                </action>
                                <action id="3" name="Set at XY" sid="4234406557452194" type="arr_items_Weapons">
                                    <param id="0" name="X">arr_items_Weapons.Width-1</param>
                                    <param id="1" name="Y">0</param>
                                    <param id="2" name="Value">&quot;medium laser&quot;</param>
                                </action>
                                <action id="3" name="Set at XY" sid="8200115984621397" type="arr_items_Weapons">
                                    <param id="0" name="X">arr_items_Weapons.Width-1</param>
                                    <param id="1" name="Y">1</param>
                                    <param id="2" name="Value">10</param>
                                </action>
                                <action id="3" name="Set at XY" sid="2645912167001083" type="arr_items_Weapons">
                                    <param id="0" name="X">arr_items_Weapons.Width-1</param>
                                    <param id="1" name="Y">2</param>
                                    <param id="2" name="Value">15</param>
                                </action>
                                <action id="3" name="Set at XY" sid="6314498264604441" type="arr_items_Weapons">
                                    <param id="0" name="X">arr_items_Weapons.Width-1</param>
                                    <param id="1" name="Y">3</param>
                                    <param id="2" name="Value">3</param>
                                </action>
                                <action id="3" name="Set at XY" sid="8726635708341578" type="arr_items_Weapons">
                                    <param id="0" name="X">arr_items_Weapons.Width-1</param>
                                    <param id="1" name="Y">4</param>
                                    <param id="2" name="Value">3</param>
                                </action>
                            </actions>
                        </event-block>
                        <event-block sid="5258242371955272">
                            <conditions />
                            <actions>
                                <action id="1" name="Set size" sid="2924817383455411" type="arr_items_Weapons">
                                    <param id="0" name="Width">arr_items_Weapons.Width+1</param>
                                    <param id="1" name="Height">arr_items_Weapons.Height</param>
                                    <param id="2" name="Depth">1</param>
                                </action>
                                <action id="3" name="Set at XY" sid="7842858348944928" type="arr_items_Weapons">
                                    <param id="0" name="X">arr_items_Weapons.Width-1</param>
                                    <param id="1" name="Y">0</param>
                                    <param id="2" name="Value">&quot;large laser&quot;</param>
                                </action>
                                <action id="3" name="Set at XY" sid="1111229452980783" type="arr_items_Weapons">
                                    <param id="0" name="X">arr_items_Weapons.Width-1</param>
                                    <param id="1" name="Y">1</param>
                                    <param id="2" name="Value">15</param>
                                </action>
                                <action id="3" name="Set at XY" sid="9876753708992288" type="arr_items_Weapons">
                                    <param id="0" name="X">arr_items_Weapons.Width-1</param>
                                    <param id="1" name="Y">2</param>
                                    <param id="2" name="Value">25</param>
                                </action>
                                <action id="3" name="Set at XY" sid="1533308489656037" type="arr_items_Weapons">
                                    <param id="0" name="X">arr_items_Weapons.Width-1</param>
                                    <param id="1" name="Y">3</param>
                                    <param id="2" name="Value">10</param>
                                </action>
                                <action id="3" name="Set at XY" sid="546250574143012" type="arr_items_Weapons">
                                    <param id="0" name="X">arr_items_Weapons.Width-1</param>
                                    <param id="1" name="Y">4</param>
                                    <param id="2" name="Value">10</param>
                                </action>
                            </actions>
                        </event-block>
                        <event-block sid="4074349993878809">
                            <conditions />
                            <actions>
                                <action id="1" name="Set size" sid="5286716557698417" type="arr_items_Weapons">
                                    <param id="0" name="Width">arr_items_Weapons.Width+1</param>
                                    <param id="1" name="Height">arr_items_Weapons.Height</param>
                                    <param id="2" name="Depth">1</param>
                                </action>
                                <action id="3" name="Set at XY" sid="8415383665697278" type="arr_items_Weapons">
                                    <param id="0" name="X">arr_items_Weapons.Width-1</param>
                                    <param id="1" name="Y">0</param>
                                    <param id="2" name="Value">&quot;missile&quot;</param>
                                </action>
                                <action id="3" name="Set at XY" sid="3180155241957015" type="arr_items_Weapons">
                                    <param id="0" name="X">arr_items_Weapons.Width-1</param>
                                    <param id="1" name="Y">1</param>
                                    <param id="2" name="Value">10</param>
                                </action>
                                <action id="3" name="Set at XY" sid="1094756682025782" type="arr_items_Weapons">
                                    <param id="0" name="X">arr_items_Weapons.Width-1</param>
                                    <param id="1" name="Y">2</param>
                                    <param id="2" name="Value">50</param>
                                </action>
                                <action id="3" name="Set at XY" sid="766506288129886" type="arr_items_Weapons">
                                    <param id="0" name="X">arr_items_Weapons.Width-1</param>
                                    <param id="1" name="Y">3</param>
                                    <param id="2" name="Value">7</param>
                                </action>
                                <action id="3" name="Set at XY" sid="4076221851295276" type="arr_items_Weapons">
                                    <param id="0" name="X">arr_items_Weapons.Width-1</param>
                                    <param id="1" name="Y">4</param>
                                    <param id="2" name="Value">3</param>
                                </action>
                            </actions>
                        </event-block>
                    </sub-events>
                </event-block>
            </sub-events>
        </event-block>
        <event-block sid="4332197772319421">
            <conditions>
                <condition id="0" name="On function" sid="1450371772744238" type="Function">
                    <param id="0" name="Name">&quot;CreateshipsDB&quot;</param>
                </condition>
            </conditions>
            <actions />
            <sub-events>
                <variable constant="0" name="localUID" sid="112020389376764" static="0" type="number">0</variable>
                <event-block sid="9621626625591234">
                    <conditions>
                        <condition id="-8" name="Compare two values" sid="8518390832233319" type="System">
                            <param id="0" name="First value">Function.ParamCount</param>
                            <param id="1" name="Comparison">4</param>
                            <param id="2" name="Second value">0</param>
                        </condition>
                    </conditions>
                    <actions>
                        <action id="-9" name="Set value" sid="6257021744057116" type="System">
                            <param id="0" name="Variable">localUID</param>
                            <param id="1" name="Value">Function.Param(0)</param>
                        </action>
                    </actions>
                </event-block>
                <event-block sid="5991681963730228">
                    <conditions>
                        <condition id="-22" name="Else" sid="4529664533389512" type="System" />
                    </conditions>
                    <actions>
                        <action id="-3" name="Create object" sid="1584402816165871" type="System">
                            <param id="0" name="Object to create">arr_shipsDB</param>
                            <param id="1" name="Layer">0</param>
                            <param id="2" name="X">0</param>
                            <param id="3" name="Y">0</param>
                        </action>
                        <action id="-9" name="Set value" sid="2111829953734300" type="System">
                            <param id="0" name="Variable">localUID</param>
                            <param id="1" name="Value">arr_shipsDB.UID</param>
                        </action>
                    </actions>
                </event-block>
                <event-block sid="2414474434704705">
                    <conditions>
                        <condition id="-14" name="Pick by unique ID" sid="5168404959902937" type="arr_shipsDB">
                            <param id="0" name="Unique ID">localUID</param>
                        </condition>
                    </conditions>
                    <actions>
                        <action id="1" name="Set return value" sid="6041627466834847" type="Function">
                            <param id="0" name="Value">localUID</param>
                        </action>
                    </actions>
                    <sub-events>
                        <event-block sid="3173616192948313">
                            <conditions />
                            <actions>
                                <action id="1" name="Set size" sid="1944298331172157" type="arr_shipsDB">
                                    <param id="0" name="Width">arr_shipsDB.Width+1</param>
                                    <param id="1" name="Height">arr_shipsDB.Height</param>
                                    <param id="2" name="Depth">1</param>
                                </action>
                                <action id="3" name="Set at XY" sid="5170100442143253" type="arr_shipsDB">
                                    <param id="0" name="X">arr_shipsDB.Width-1</param>
                                    <param id="1" name="Y">0</param>
                                    <param id="2" name="Value">&quot;Frigate&quot;</param>
                                </action>
                                <action id="3" name="Set at XY" sid="5414404433950998" type="arr_shipsDB">
                                    <param id="0" name="X">arr_shipsDB.Width-1</param>
                                    <param id="1" name="Y">1</param>
                                    <param id="2" name="Value">3</param>
                                </action>
                                <action id="3" name="Set at XY" sid="7196501180007400" type="arr_shipsDB">
                                    <param id="0" name="X">arr_shipsDB.Width-1</param>
                                    <param id="1" name="Y">2</param>
                                    <param id="2" name="Value">0</param>
                                </action>
                                <action id="3" name="Set at XY" sid="6827903573781545" type="arr_shipsDB">
                                    <param id="0" name="X">arr_shipsDB.Width-1</param>
                                    <param id="1" name="Y">3</param>
                                    <param id="2" name="Value">0</param>
                                </action>
                                <action id="3" name="Set at XY" sid="2361397420530468" type="arr_shipsDB">
                                    <param id="0" name="X">arr_shipsDB.Width-1</param>
                                    <param id="1" name="Y">4</param>
                                    <param id="2" name="Value">1</param>
                                </action>
                                <action id="3" name="Set at XY" sid="3881628684922302" type="arr_shipsDB">
                                    <param id="0" name="X">arr_shipsDB.Width-1</param>
                                    <param id="1" name="Y">5</param>
                                    <param id="2" name="Value">1</param>
                                </action>
                                <action id="3" name="Set at XY" sid="5574887717495953" type="arr_shipsDB">
                                    <param id="0" name="X">arr_shipsDB.Width-1</param>
                                    <param id="1" name="Y">6</param>
                                    <param id="2" name="Value">1</param>
                                </action>
                                <action id="3" name="Set at XY" sid="7942728049289419" type="arr_shipsDB">
                                    <param id="0" name="X">arr_shipsDB.Width-1</param>
                                    <param id="1" name="Y">7</param>
                                    <param id="2" name="Value">35</param>
                                </action>
                            </actions>
                        </event-block>
                        <event-block sid="284610401097919">
                            <conditions />
                            <actions>
                                <action id="1" name="Set size" sid="9653975266986876" type="arr_shipsDB">
                                    <param id="0" name="Width">arr_shipsDB.Width+1</param>
                                    <param id="1" name="Height">arr_shipsDB.Height</param>
                                    <param id="2" name="Depth">1</param>
                                </action>
                                <action id="3" name="Set at XY" sid="5582106589252935" type="arr_shipsDB">
                                    <param id="0" name="X">arr_shipsDB.Width-1</param>
                                    <param id="1" name="Y">0</param>
                                    <param id="2" name="Value">&quot;Cruiser&quot;</param>
                                </action>
                                <action id="3" name="Set at XY" sid="7393970365892281" type="arr_shipsDB">
                                    <param id="0" name="X">arr_shipsDB.Width-1</param>
                                    <param id="1" name="Y">1</param>
                                    <param id="2" name="Value">4</param>
                                </action>
                                <action id="3" name="Set at XY" sid="4431098990594007" type="arr_shipsDB">
                                    <param id="0" name="X">arr_shipsDB.Width-1</param>
                                    <param id="1" name="Y">2</param>
                                    <param id="2" name="Value">0</param>
                                </action>
                                <action id="3" name="Set at XY" sid="3403936755551636" type="arr_shipsDB">
                                    <param id="0" name="X">arr_shipsDB.Width-1</param>
                                    <param id="1" name="Y">3</param>
                                    <param id="2" name="Value">1</param>
                                </action>
                                <action id="3" name="Set at XY" sid="1008524849392186" type="arr_shipsDB">
                                    <param id="0" name="X">arr_shipsDB.Width-1</param>
                                    <param id="1" name="Y">4</param>
                                    <param id="2" name="Value">1</param>
                                </action>
                                <action id="3" name="Set at XY" sid="4067151175643273" type="arr_shipsDB">
                                    <param id="0" name="X">arr_shipsDB.Width-1</param>
                                    <param id="1" name="Y">5</param>
                                    <param id="2" name="Value">1</param>
                                </action>
                                <action id="3" name="Set at XY" sid="7874921092809754" type="arr_shipsDB">
                                    <param id="0" name="X">arr_shipsDB.Width-1</param>
                                    <param id="1" name="Y">6</param>
                                    <param id="2" name="Value">1</param>
                                </action>
                                <action id="3" name="Set at XY" sid="7910954689005942" type="arr_shipsDB">
                                    <param id="0" name="X">arr_shipsDB.Width-1</param>
                                    <param id="1" name="Y">7</param>
                                    <param id="2" name="Value">50</param>
                                </action>
                            </actions>
                        </event-block>
                        <event-block sid="2013346296796119">
                            <conditions />
                            <actions>
                                <action id="1" name="Set size" sid="274163141591059" type="arr_shipsDB">
                                    <param id="0" name="Width">arr_shipsDB.Width+1</param>
                                    <param id="1" name="Height">arr_shipsDB.Height</param>
                                    <param id="2" name="Depth">1</param>
                                </action>
                                <action id="3" name="Set at XY" sid="7688510329137597" type="arr_shipsDB">
                                    <param id="0" name="X">arr_shipsDB.Width-1</param>
                                    <param id="1" name="Y">0</param>
                                    <param id="2" name="Value">&quot;Dreadnought&quot;</param>
                                </action>
                                <action id="3" name="Set at XY" sid="7103201569918608" type="arr_shipsDB">
                                    <param id="0" name="X">arr_shipsDB.Width-1</param>
                                    <param id="1" name="Y">1</param>
                                    <param id="2" name="Value">9</param>
                                </action>
                                <action id="3" name="Set at XY" sid="1820333813114048" type="arr_shipsDB">
                                    <param id="0" name="X">arr_shipsDB.Width-1</param>
                                    <param id="1" name="Y">2</param>
                                    <param id="2" name="Value">1</param>
                                </action>
                                <action id="3" name="Set at XY" sid="2820017752251845" type="arr_shipsDB">
                                    <param id="0" name="X">arr_shipsDB.Width-1</param>
                                    <param id="1" name="Y">3</param>
                                    <param id="2" name="Value">1</param>
                                </action>
                                <action id="3" name="Set at XY" sid="8329383471288906" type="arr_shipsDB">
                                    <param id="0" name="X">arr_shipsDB.Width-1</param>
                                    <param id="1" name="Y">4</param>
                                    <param id="2" name="Value">2</param>
                                </action>
                                <action id="3" name="Set at XY" sid="5090407914510772" type="arr_shipsDB">
                                    <param id="0" name="X">arr_shipsDB.Width-1</param>
                                    <param id="1" name="Y">5</param>
                                    <param id="2" name="Value">2</param>
                                </action>
                                <action id="3" name="Set at XY" sid="9631855447299886" type="arr_shipsDB">
                                    <param id="0" name="X">arr_shipsDB.Width-1</param>
                                    <param id="1" name="Y">6</param>
                                    <param id="2" name="Value">2</param>
                                </action>
                                <action id="3" name="Set at XY" sid="2500931752883230" type="arr_shipsDB">
                                    <param id="0" name="X">arr_shipsDB.Width-1</param>
                                    <param id="1" name="Y">7</param>
                                    <param id="2" name="Value">75</param>
                                </action>
                            </actions>
                        </event-block>
                        <event-block sid="4992598055578802">
                            <conditions />
                            <actions>
                                <action id="1" name="Set size" sid="5985763555557712" type="arr_shipsDB">
                                    <param id="0" name="Width">arr_shipsDB.Width+1</param>
                                    <param id="1" name="Height">arr_shipsDB.Height</param>
                                    <param id="2" name="Depth">1</param>
                                </action>
                                <action id="3" name="Set at XY" sid="3159960370548397" type="arr_shipsDB">
                                    <param id="0" name="X">arr_shipsDB.Width-1</param>
                                    <param id="1" name="Y">0</param>
                                    <param id="2" name="Value">&quot;Battleship&quot;</param>
                                </action>
                                <action id="3" name="Set at XY" sid="2523383753703238" type="arr_shipsDB">
                                    <param id="0" name="X">arr_shipsDB.Width-1</param>
                                    <param id="1" name="Y">1</param>
                                    <param id="2" name="Value">13</param>
                                </action>
                                <action id="3" name="Set at XY" sid="4337302995761971" type="arr_shipsDB">
                                    <param id="0" name="X">arr_shipsDB.Width-1</param>
                                    <param id="1" name="Y">2</param>
                                    <param id="2" name="Value">2</param>
                                </action>
                                <action id="3" name="Set at XY" sid="6731478488359994" type="arr_shipsDB">
                                    <param id="0" name="X">arr_shipsDB.Width-1</param>
                                    <param id="1" name="Y">3</param>
                                    <param id="2" name="Value">2</param>
                                </action>
                                <action id="3" name="Set at XY" sid="7794024123481656" type="arr_shipsDB">
                                    <param id="0" name="X">arr_shipsDB.Width-1</param>
                                    <param id="1" name="Y">4</param>
                                    <param id="2" name="Value">3</param>
                                </action>
                                <action id="3" name="Set at XY" sid="6545913658856799" type="arr_shipsDB">
                                    <param id="0" name="X">arr_shipsDB.Width-1</param>
                                    <param id="1" name="Y">5</param>
                                    <param id="2" name="Value">3</param>
                                </action>
                                <action id="3" name="Set at XY" sid="5294921331812031" type="arr_shipsDB">
                                    <param id="0" name="X">arr_shipsDB.Width-1</param>
                                    <param id="1" name="Y">6</param>
                                    <param id="2" name="Value">3</param>
                                </action>
                                <action id="3" name="Set at XY" sid="2794535542913845" type="arr_shipsDB">
                                    <param id="0" name="X">arr_shipsDB.Width-1</param>
                                    <param id="1" name="Y">7</param>
                                    <param id="2" name="Value">100</param>
                                </action>
                            </actions>
                        </event-block>
                    </sub-events>
                </event-block>
            </sub-events>
        </event-block>
        <event-block sid="2506225321146232">
            <conditions>
                <condition id="0" name="On function" sid="9588898175117706" type="Function">
                    <param id="0" name="Name">&quot;Createarr_PCShipAft&quot;</param>
                </condition>
            </conditions>
            <actions />
            <sub-events>
                <variable constant="0" name="localUID" sid="8993562813558705" static="0" type="number">0</variable>
                <event-block sid="9079978278861455">
                    <conditions>
                        <condition id="-8" name="Compare two values" sid="466207239744230" type="System">
                            <param id="0" name="First value">Function.ParamCount</param>
                            <param id="1" name="Comparison">4</param>
                            <param id="2" name="Second value">0</param>
                        </condition>
                    </conditions>
                    <actions>
                        <action id="-9" name="Set value" sid="5516907017668566" type="System">
                            <param id="0" name="Variable">localUID</param>
                            <param id="1" name="Value">Function.Param(0)</param>
                        </action>
                    </actions>
                </event-block>
                <event-block sid="7053142934690485">
                    <conditions>
                        <condition id="-22" name="Else" sid="5815285076553047" type="System" />
                    </conditions>
                    <actions>
                        <action id="-3" name="Create object" sid="2163798032354706" type="System">
                            <param id="0" name="Object to create">arr_PCShipAft</param>
                            <param id="1" name="Layer">0</param>
                            <param id="2" name="X">0</param>
                            <param id="3" name="Y">0</param>
                        </action>
                        <action id="-9" name="Set value" sid="8119403844658752" type="System">
                            <param id="0" name="Variable">localUID</param>
                            <param id="1" name="Value">arr_PCShipAft.UID</param>
                        </action>
                    </actions>
                </event-block>
                <event-block sid="9979758591205050">
                    <conditions>
                        <condition id="-14" name="Pick by unique ID" sid="6862853277823325" type="arr_PCShipAft">
                            <param id="0" name="Unique ID">localUID</param>
                        </condition>
                    </conditions>
                    <actions>
                        <action id="1" name="Set return value" sid="6155009336937334" type="Function">
                            <param id="0" name="Value">localUID</param>
                        </action>
                    </actions>
                </event-block>
            </sub-events>
        </event-block>
        <event-block sid="9590034464106516">
            <conditions>
                <condition id="0" name="On function" sid="8733509593915943" type="Function">
                    <param id="0" name="Name">&quot;Createarr_PCShipHull&quot;</param>
                </condition>
            </conditions>
            <actions />
            <sub-events>
                <variable constant="0" name="localUID" sid="3427414370959977" static="0" type="number">0</variable>
                <event-block sid="5340009964174296">
                    <conditions>
                        <condition id="-8" name="Compare two values" sid="862232729640359" type="System">
                            <param id="0" name="First value">Function.ParamCount</param>
                            <param id="1" name="Comparison">4</param>
                            <param id="2" name="Second value">0</param>
                        </condition>
                    </conditions>
                    <actions>
                        <action id="-9" name="Set value" sid="6162533353190795" type="System">
                            <param id="0" name="Variable">localUID</param>
                            <param id="1" name="Value">Function.Param(0)</param>
                        </action>
                    </actions>
                </event-block>
                <event-block sid="1351244106803482">
                    <conditions>
                        <condition id="-22" name="Else" sid="8112560642792265" type="System" />
                    </conditions>
                    <actions>
                        <action id="-3" name="Create object" sid="127846174185200" type="System">
                            <param id="0" name="Object to create">arr_PCShipHull</param>
                            <param id="1" name="Layer">0</param>
                            <param id="2" name="X">0</param>
                            <param id="3" name="Y">0</param>
                        </action>
                        <action id="-9" name="Set value" sid="5918569429607598" type="System">
                            <param id="0" name="Variable">localUID</param>
                            <param id="1" name="Value">arr_PCShipHull.UID</param>
                        </action>
                    </actions>
                </event-block>
                <event-block sid="301104340505111">
                    <conditions>
                        <condition id="-14" name="Pick by unique ID" sid="2632079418498631" type="arr_PCShipHull">
                            <param id="0" name="Unique ID">localUID</param>
                        </condition>
                    </conditions>
                    <actions>
                        <action id="1" name="Set return value" sid="5381288458441991" type="Function">
                            <param id="0" name="Value">localUID</param>
                        </action>
                    </actions>
                </event-block>
            </sub-events>
        </event-block>
        <event-block sid="7470167235936448">
            <conditions>
                <condition id="0" name="On function" sid="7352299389723532" type="Function">
                    <param id="0" name="Name">&quot;Createarr_PCShipPort&quot;</param>
                </condition>
            </conditions>
            <actions />
            <sub-events>
                <variable constant="0" name="localUID" sid="8213820856868580" static="0" type="number">0</variable>
                <event-block sid="3677368854229588">
                    <conditions>
                        <condition id="-8" name="Compare two values" sid="2743309536761253" type="System">
                            <param id="0" name="First value">Function.ParamCount</param>
                            <param id="1" name="Comparison">4</param>
                            <param id="2" name="Second value">0</param>
                        </condition>
                    </conditions>
                    <actions>
                        <action id="-9" name="Set value" sid="787859143849799" type="System">
                            <param id="0" name="Variable">localUID</param>
                            <param id="1" name="Value">Function.Param(0)</param>
                        </action>
                    </actions>
                </event-block>
                <event-block sid="7931046261369262">
                    <conditions>
                        <condition id="-22" name="Else" sid="8911619782902555" type="System" />
                    </conditions>
                    <actions>
                        <action id="-3" name="Create object" sid="7781832505161221" type="System">
                            <param id="0" name="Object to create">arr_PCShipPort</param>
                            <param id="1" name="Layer">0</param>
                            <param id="2" name="X">0</param>
                            <param id="3" name="Y">0</param>
                        </action>
                        <action id="-9" name="Set value" sid="6550573696375601" type="System">
                            <param id="0" name="Variable">localUID</param>
                            <param id="1" name="Value">arr_PCShipPort.UID</param>
                        </action>
                    </actions>
                </event-block>
                <event-block sid="6782444565100355">
                    <conditions>
                        <condition id="-14" name="Pick by unique ID" sid="836950031110504" type="arr_PCShipPort">
                            <param id="0" name="Unique ID">localUID</param>
                        </condition>
                    </conditions>
                    <actions>
                        <action id="1" name="Set return value" sid="5094396110305266" type="Function">
                            <param id="0" name="Value">localUID</param>
                        </action>
                    </actions>
                </event-block>
            </sub-events>
        </event-block>
        <event-block sid="1777241078823251">
            <conditions>
                <condition id="0" name="On function" sid="5750312112592941" type="Function">
                    <param id="0" name="Name">&quot;Createarr_PCShipProw&quot;</param>
                </condition>
            </conditions>
            <actions />
            <sub-events>
                <variable constant="0" name="localUID" sid="5502721188650388" static="0" type="number">0</variable>
                <event-block sid="4148662956508187">
                    <conditions>
                        <condition id="-8" name="Compare two values" sid="3677133254145707" type="System">
                            <param id="0" name="First value">Function.ParamCount</param>
                            <param id="1" name="Comparison">4</param>
                            <param id="2" name="Second value">0</param>
                        </condition>
                    </conditions>
                    <actions>
                        <action id="-9" name="Set value" sid="3650555830616127" type="System">
                            <param id="0" name="Variable">localUID</param>
                            <param id="1" name="Value">Function.Param(0)</param>
                        </action>
                    </actions>
                </event-block>
                <event-block sid="813607171325748">
                    <conditions>
                        <condition id="-22" name="Else" sid="5862672719406253" type="System" />
                    </conditions>
                    <actions>
                        <action id="-3" name="Create object" sid="1346561293332235" type="System">
                            <param id="0" name="Object to create">arr_PCShipProw</param>
                            <param id="1" name="Layer">0</param>
                            <param id="2" name="X">0</param>
                            <param id="3" name="Y">0</param>
                        </action>
                        <action id="-9" name="Set value" sid="5868491254176655" type="System">
                            <param id="0" name="Variable">localUID</param>
                            <param id="1" name="Value">arr_PCShipProw.UID</param>
                        </action>
                    </actions>
                </event-block>
                <event-block sid="5901272864324858">
                    <conditions>
                        <condition id="-14" name="Pick by unique ID" sid="5947579212015463" type="arr_PCShipProw">
                            <param id="0" name="Unique ID">localUID</param>
                        </condition>
                    </conditions>
                    <actions>
                        <action id="1" name="Set return value" sid="8782212767106987" type="Function">
                            <param id="0" name="Value">localUID</param>
                        </action>
                    </actions>
                </event-block>
            </sub-events>
        </event-block>
        <event-block sid="8217179808007132">
            <conditions>
                <condition id="0" name="On function" sid="7036026466175852" type="Function">
                    <param id="0" name="Name">&quot;Createarr_PCShipSB&quot;</param>
                </condition>
            </conditions>
            <actions />
            <sub-events>
                <variable constant="0" name="localUID" sid="3322392189141104" static="0" type="number">0</variable>
                <event-block sid="4926517666045121">
                    <conditions>
                        <condition id="-8" name="Compare two values" sid="2763819872801134" type="System">
                            <param id="0" name="First value">Function.ParamCount</param>
                            <param id="1" name="Comparison">4</param>
                            <param id="2" name="Second value">0</param>
                        </condition>
                    </conditions>
                    <actions>
                        <action id="-9" name="Set value" sid="6636586266568756" type="System">
                            <param id="0" name="Variable">localUID</param>
                            <param id="1" name="Value">Function.Param(0)</param>
                        </action>
                    </actions>
                </event-block>
                <event-block sid="7013565394832654">
                    <conditions>
                        <condition id="-22" name="Else" sid="3678855304725390" type="System" />
                    </conditions>
                    <actions>
                        <action id="-3" name="Create object" sid="6230099900610399" type="System">
                            <param id="0" name="Object to create">arr_PCShipSB</param>
                            <param id="1" name="Layer">0</param>
                            <param id="2" name="X">0</param>
                            <param id="3" name="Y">0</param>
                        </action>
                        <action id="-9" name="Set value" sid="1022968147209376" type="System">
                            <param id="0" name="Variable">localUID</param>
                            <param id="1" name="Value">arr_PCShipSB.UID</param>
                        </action>
                    </actions>
                </event-block>
                <event-block sid="5860344368879437">
                    <conditions>
                        <condition id="-14" name="Pick by unique ID" sid="4815060031626807" type="arr_PCShipSB">
                            <param id="0" name="Unique ID">localUID</param>
                        </condition>
                    </conditions>
                    <actions>
                        <action id="1" name="Set return value" sid="3051685659518029" type="Function">
                            <param id="0" name="Value">localUID</param>
                        </action>
                    </actions>
                </event-block>
            </sub-events>
        </event-block>
    </events>
</c2eventsheet>
